huaweicloudsdkcodeartsbuild/__init__.py
huaweicloudsdkcodeartsbuild/v3/__init__.py
huaweicloudsdkcodeartsbuild/v3/codeartsbuild_async_client.py
huaweicloudsdkcodeartsbuild/v3/codeartsbuild_client.py
huaweicloudsdkcodeartsbuild/v3/model/__init__.py
huaweicloudsdkcodeartsbuild/v3/model/add_favourite_custom_template_request.py
huaweicloudsdkcodeartsbuild/v3/model/add_favourite_custom_template_response.py
huaweicloudsdkcodeartsbuild/v3/model/add_favourite_official_template_request.py
huaweicloudsdkcodeartsbuild/v3/model/add_favourite_official_template_response.py
huaweicloudsdkcodeartsbuild/v3/model/add_favourite_task_request.py
huaweicloudsdkcodeartsbuild/v3/model/add_favourite_task_response.py
huaweicloudsdkcodeartsbuild/v3/model/add_keystore_permission_request.py
huaweicloudsdkcodeartsbuild/v3/model/add_keystore_permission_request_body.py
huaweicloudsdkcodeartsbuild/v3/model/add_keystore_permission_response.py
huaweicloudsdkcodeartsbuild/v3/model/add_keystore_permission_response_body.py
huaweicloudsdkcodeartsbuild/v3/model/apply_project_permission_request.py
huaweicloudsdkcodeartsbuild/v3/model/apply_project_permission_response.py
huaweicloudsdkcodeartsbuild/v3/model/batch_delete_build_jobs_request.py
huaweicloudsdkcodeartsbuild/v3/model/batch_delete_build_jobs_request_body.py
huaweicloudsdkcodeartsbuild/v3/model/batch_delete_build_jobs_response.py
huaweicloudsdkcodeartsbuild/v3/model/batch_update_job_role_permission_request.py
huaweicloudsdkcodeartsbuild/v3/model/batch_update_job_role_permission_response.py
huaweicloudsdkcodeartsbuild/v3/model/brief_record_items.py
huaweicloudsdkcodeartsbuild/v3/model/build_info_record.py
huaweicloudsdkcodeartsbuild/v3/model/build_info_record_commit_info.py
huaweicloudsdkcodeartsbuild/v3/model/build_parameter.py
huaweicloudsdkcodeartsbuild/v3/model/build_params.py
huaweicloudsdkcodeartsbuild/v3/model/build_params_body_result.py
huaweicloudsdkcodeartsbuild/v3/model/build_record.py
huaweicloudsdkcodeartsbuild-3.1.184.dist-info/METADATA
huaweicloudsdkcodeartsbuild-3.1.184.dist-info/WHEEL
huaweicloudsdkcodeartsbuild-3.1.184.dist-info/licenses/LICENSE
huaweicloudsdkcodeartsbuild-3.1.184.dist-info/RECORD
